hygieia/__init__.py
hygieia/clinical_feature_selection.py
hygieia/genomic_feature_selection.py
hygieia-1.0.2.dist-info/LICENSE
hygieia-1.0.2.dist-info/METADATA
hygieia-1.0.2.dist-info/WHEEL
hygieia-1.0.2.dist-info/top_level.txt
hygieia-1.0.2.dist-info/RECORD
