Metadata-Version: 2.1
Name: hygieia
Version: 1.0.2
Summary: Hygieia utilizes feature selection to predict the clinical and genomic basis of disease.
Author: Will DeGroat, Vignesh Venkat, Habiba Abdelhalim, , Widnie Pierre-Louis, Dr. Zeeshan Ahmed
Author-email: will.degroat@gmail.com, zahmed@ifh.rutgers.edu
License: GNU General Public License v3.0
Platform: UNKNOWN
License-File: LICENSE
Requires-Dist: pandas
Requires-Dist: sklearn
Requires-Dist: matplotlib
Requires-Dist: seaborn
Requires-Dist: scikit-learn
